kube_ops/__about__.py
kube_ops/__init__.py
kube_ops/api.py
kube_ops/common.py
kube_ops/config.py
kube_ops/enums.py
kube_ops/manifests.py
kube_ops/templates.py
kube_ops-1.1.1.dist-info/METADATA
kube_ops-1.1.1.dist-info/WHEEL
kube_ops-1.1.1.dist-info/licenses/LICENSE
kube_ops-1.1.1.dist-info/RECORD
