Metadata-Version: 2.3
Name: kube-ops
Version: 1.1.1
Summary: Kubernetes OOP
Project-URL: Homepage, https://github.com/myback/kube-ops
Project-URL: Bug Tracker, https://github.com/myback/kube-ops/issues
Author-email: myback <54638513+myback@users.noreply.github.com>
License: MIT License
License-File: LICENSE
Classifier: Development Status :: 4 - Beta
Classifier: Programming Language :: Python
Classifier: Programming Language :: Python :: 3.11
Classifier: Programming Language :: Python :: 3.12
Classifier: Programming Language :: Python :: Implementation :: CPython
Classifier: Programming Language :: Python :: Implementation :: PyPy
Requires-Python: >=3.11
Requires-Dist: kubernetes~=30.1.0
Requires-Dist: pyyaml~=6.0.1
